linguistics_robin/__init__.py
linguistics_robin/exceptions.py
linguistics_robin/utils.py
linguistics_robin/distance_metrics/__init__.py
linguistics_robin/distance_metrics/hamming.py
linguistics_robin/distance_metrics/levenshtein.py
linguistics_robin/phonetics/__init__.py
linguistics_robin/phonetics/caverphone.py
linguistics_robin/phonetics/caverphone2.py
linguistics_robin/phonetics/doublemetaphone.py
linguistics_robin/phonetics/fuzzy_soundex.py
linguistics_robin/phonetics/lein.py
linguistics_robin/phonetics/metaphone.py
linguistics_robin/phonetics/mra.py
linguistics_robin/phonetics/nysiis.py
linguistics_robin/phonetics/phonetic_algorithm.py
linguistics_robin/phonetics/refined_soundex.py
linguistics_robin/phonetics/soundex.py
linguistics_robin-0.5.9.dist-info/licenses/LICENSE.md
linguistics_robin-0.5.9.dist-info/WHEEL
linguistics_robin-0.5.9.dist-info/METADATA
linguistics_robin-0.5.9.dist-info/RECORD
