Metadata-Version: 2.4
Name: linguistics_robin
Version: 0.5.9
Summary: A Python 3 linguistics collection library.
Home-page: https://github.com/linuxgoose/linguistics-robin
Author: Jordan Robinson
Author-email: hello@jordanrobinson.org
Classifier: License :: OSI Approved :: MIT License
Classifier: Programming Language :: Python :: 3
Classifier: Intended Audience :: Developers
Classifier: Topic :: Software Development :: Libraries :: Python Modules
License-File: LICENSE.md
Requires-Dist: unidecode >=1,<2
